edwh_b2_plugin/__about__.py
edwh_b2_plugin/__init__.py
edwh_b2_plugin/b2_plugin.py
edwh_b2_plugin-0.2.4.dist-info/METADATA
edwh_b2_plugin-0.2.4.dist-info/WHEEL
edwh_b2_plugin-0.2.4.dist-info/entry_points.txt
edwh_b2_plugin-0.2.4.dist-info/licenses/LICENSE.txt
edwh_b2_plugin-0.2.4.dist-info/RECORD
